skoll/__init__.py
skoll/create_app.py
skoll/utils.py
skoll/db/__init__.py
skoll/db/base.py
skoll/domain/__init__.py
skoll/domain/errors.py
skoll/domain/result.py
skoll/mediator/__init__.py
skoll/mediator/base.py
skoll-0.1.0.dist-info/METADATA
skoll-0.1.0.dist-info/WHEEL
skoll-0.1.0.dist-info/entry_points.txt
skoll-0.1.0.dist-info/RECORD
