Metadata-Version: 2.4
Name: skoll
Version: 0.1.0
Summary: A single package to that provide a basic API python framework based on starlette and some domain driven design concepts
Author-email: Monzon Diarra <diarramonzon4@gmail.com>
Requires-Python: >=3.13
Requires-Dist: aiohttp>=3.13.3
Requires-Dist: asyncpg>=0.31.0
Requires-Dist: attrs>=25.4.0
Requires-Dist: certifi>=2026.1.4
Requires-Dist: starlette>=0.49.3
Requires-Dist: ulid>=1.1
